remarkable_update_image.cpython-313-darwin.so
remarkable_update_image.pyi
remarkable_update_image-1.3.1.dist-info/licenses/LICENSE
remarkable_update_image-1.3.1.dist-info/METADATA
remarkable_update_image-1.3.1.dist-info/WHEEL
remarkable_update_image-1.3.1.dist-info/top_level.txt
remarkable_update_image-1.3.1.dist-info/RECORD
