Metadata-Version: 2.4
Name: remarkable_update_image
Version: 1.3.1
Summary: Read reMarkable update images
Author-email: Eeems <eeems@eeems.email>
License-Expression: MIT
Project-URL: Homepage, https://github.com/Eeems/remarkable-update-image
Project-URL: Repository, https://github.com/Eeems/remarkable-update-image.git
Project-URL: Issues, https://github.com/Eeems/remarkable-update-image/issues
Classifier: Development Status :: 5 - Production/Stable
Classifier: Environment :: Console
Classifier: Intended Audience :: Developers
Classifier: Operating System :: POSIX :: Linux
Classifier: Programming Language :: Python :: 3 :: Only
Classifier: Programming Language :: Python :: 3
Classifier: Programming Language :: Python :: 3.11
Classifier: Programming Language :: Python :: 3.12
Classifier: Programming Language :: Python :: 3.13
Classifier: Topic :: System :: Filesystems
Classifier: Topic :: Utilities
Requires-Python: <3.14,>=3.11
License-File: LICENSE
Requires-Dist: cryptography==46.0.3
Requires-Dist: protobuf==5.29.5
Requires-Dist: ext4==1.2.2
Requires-Dist: libconf==2.0.1
Requires-Dist: indexed-gzip==1.10.1
Dynamic: license-file
